odoo/addons/sync_sale_picking_cost/README.rst
odoo/addons/sync_sale_picking_cost/__init__.py
odoo/addons/sync_sale_picking_cost/__manifest__.py
odoo/addons/sync_sale_picking_cost/models/__init__.py
odoo/addons/sync_sale_picking_cost/models/product_template.py
odoo/addons/sync_sale_picking_cost/models/sale_order_line.py
odoo/addons/sync_sale_picking_cost/models/stock_move.py
odoo/addons/sync_sale_picking_cost/readme/CONTRIBUTORS.rst
odoo/addons/sync_sale_picking_cost/readme/DESCRIPTION.rst
odoo/addons/sync_sale_picking_cost/readme/INSTALL.rst
odoo/addons/sync_sale_picking_cost/static/description/icon.png
odoo/addons/sync_sale_picking_cost/static/description/index.html
odoo/addons/sync_sale_picking_cost/tests/__init__.py
odoo/addons/sync_sale_picking_cost/tests/test_sync_sale_picking_cost.py
odoo_addon_sync_sale_picking_cost-15.0.2.0.0.dist-info/METADATA
odoo_addon_sync_sale_picking_cost-15.0.2.0.0.dist-info/WHEEL
odoo_addon_sync_sale_picking_cost-15.0.2.0.0.dist-info/top_level.txt
odoo_addon_sync_sale_picking_cost-15.0.2.0.0.dist-info/RECORD
