Metadata-Version: 2.1
Name: odoo-addon-sync_sale_picking_cost
Version: 15.0.2.0.0
Requires-Python: >=3.8
Requires-Dist: odoo-addon-stock_valuation_fifo_lot>=15.0dev,<15.1dev
Requires-Dist: odoo>=15.0a,<15.1dev
Summary: Sync Sale Picking Cost
Home-page: https://github.com/sygel-technology/sy-margin-analysis
License: AGPL-3
Author: Sygel, Odoo Community Association (OCA)
Author-email: support@odoo-community.org
Classifier: Programming Language :: Python
Classifier: Framework :: Odoo
Classifier: Framework :: Odoo :: 15.0
Classifier: License :: OSI Approved :: GNU Affero General Public License v3
Classifier: Development Status :: 3 - Alpha
